EJ1/src/flip_flop_t.v
//Flip flop T implementation
module flip_flop_T (Clock, T, Q, not_Q, reset);
    input Clock, T, reset;
    output reg Q, not_Q; 
    always @(negedge reset, posedge Clock) begin
        if (reset == 0) begin
            Q = 1;
            not_Q = 0;
        end 
        else if (T == 1) begin
            Q <= ~Q;
            not_Q <= Q;
        end 
    end
endmodule

EJ1/src/state_machine.v
//verilog ej2
module fsm (Clock, Resetn, i, s, l1, l2);
    input Clock, Resetn, i, s;
    output reg l1, l2;
    wire out1, no_out1;
    reg noi = 0, nos = 0, in = 0, out2 = 0, out3 = 0;
    flip_flop_T fft(in, 1'b1, out1, no_out1, Resetn);
    // As this fsm don't have a flip-flop stage we implement it directly with logic gates
    always @(i, s) begin
        noi = ~i;
        nos = ~s;
        in <= i & nos;
        out3 <= in & out1;
        out2 <= in & no_out1;
        l1 <= noi | out3;
        l2 <= noi | out2;        
    end
endmodule

EJ2/src/clock.v
`timescale 100us / 100us
module clock_gen(clk);

parameter PERIOD = 10;

output reg clk;
	 
always
	begin: CLOCK_DRIVER
		clk <= 1'b0;
		#(PERIOD/2);
		clk <= 1'b1;
		#(PERIOD/2);
	end
endmodule

EJ1/src/ej1.v
// Defining timescale
`timescale 100us / 100us
module test();

    wire clock, z;
    reg reset, i, s;
    wire led1, led2;
    // Instacnes to be used
    clock_gen #(.PERIOD(2)) my_clock(clock);
    fsm my_fsm(clock, reset, i, s, led1, led2);

    // Test bench
    initial begin: TEST
        #2 reset = 0;
        #2 reset = 1;

        s = 1; // First transition adjust the flip-flop T
        i = 1;
        s = 0;
        i = 1;
        
        #2 
        s = 1;
        i = 1;
        #4
        #2 $display("Conditions: S=%b, I=%b -- Plumbs: P1=%b, P2=%b", s, i, led1, led2);
        
        #2 
        s = 0;
        i = 1;
        #4
        #2 $display("Conditions: S=%b, I=%b -- Plumbs: P1=%b, P2=%b", s, i, led1, led2);
        
        #2 
        s = 1;
        i = 1;
        #4
        #2 $display("Conditions: S=%b, I=%b -- Plumbs: P1=%b, P2=%b", s, i, led1, led2);
        
        #2 
        s = 0;
        i = 1;
        #4
        #2 $display("Conditions: S=%b, I=%b -- Plumbs: P1=%b, P2=%b", s, i, led1, led2);
        
        #2 
        s = 0;
        i = 0;
        #4
        #2 $display("Conditions: S=%b, I=%b -- Plumbs: P1=%b, P2=%b", s, i, led1, led2);
        
        #2 
        s = 0;
        i = 1;
        #4
        #2 $display("Conditions: S=%b, I=%b -- Plumbs: P1=%b, P2=%b", s, i, led1, led2);
        
        #2 
        s = 0;
        i = 0;
        #4
        #2 $display("Conditions: S=%b, I=%b -- Plumbs: P1=%b, P2=%b", s, i, led1, led2);
        
        
        
        $finish;
    end

    // Gtkwave file creation
    initial begin: GTKWAVE_FILE
        $dumpfile("bin/output.vcd");
        $dumpvars(0, test);
    end
endmodule

EJ1/bin/output.vcd
$date
	Thu Nov 14 01:11:13 2019
$end
$version
	Icarus Verilog
$end
$timescale
	100us
$end
$scope module test $end
$var wire 1 ! led2 $end
$var wire 1 " led1 $end
$var wire 1 # clock $end
$var reg 1 $ i $end
$var reg 1 % reset $end
$var reg 1 & s $end
$scope module my_clock $end
$var reg 1 # clk $end
$scope begin CLOCK_DRIVER $end
$upscope $end
$upscope $end
$scope module my_fsm $end
$var wire 1 # Clock $end
$var wire 1 % Resetn $end
$var wire 1 $ i $end
$var wire 1 & s $end
$var wire 1 ' out1 $end
$var wire 1 ( no_out1 $end
$var reg 1 ) in $end
$var reg 1 " l1 $end
$var reg 1 ! l2 $end
$var reg 1 * noi $end
$var reg 1 + nos $end
$var reg 1 , out2 $end
$var reg 1 - out3 $end
$scope module fft $end
$var wire 1 ) Clock $end
$var wire 1 . T $end
$var wire 1 % reset $end
$var reg 1 ' Q $end
$var reg 1 ( not_Q $end
$upscope $end
$upscope $end
$scope begin GTKWAVE_FILE $end
$upscope $end
$scope begin TEST $end
$upscope $end
$upscope $end
$enddefinitions $end
#0
$dumpvars
1.
0-
0,
0+
0*
0)
x(
x'
x&
x%
x$
0#
x"
x!
$end
#1
1#
#2
0#
0(
1'
0%
#3
1#
#4
1(
0'
0!
0"
1)
0#
1+
1$
0&
1%
#5
1#
#6
1,
0)
0#
0+
1&
#7
1#
#8
0#
#9
1#
#10
0#
#11
1#
#12
0#
#13
1#
#14
0(
1'
1!
0,
1)
0#
1+
0&
#15
1#
#16
0#
#17
1#
#18
0#
#19
1#
#20
0#
#21
1#
#22
0!
1-
0)
0#
0+
1&
#23
1#
#24
0#
#25
1#
#26
0#
#27
1#
#28
0#
#29
1#
#30
1(
0'
1"
0-
1)
0#
1+
0&
#31
1#
#32
0#
#33
1#
#34
0#
#35
1#
#36
0#
#37
1#
#38
1!
1,
0)
0#
1*
0$
#39
1#
#40
0#
#41
1#
#42
0#
#43
1#
#44
0#
#45
1#
#46
0(
1'
0"
0,
1)
0#
0*
1$
#47
1#
#48
0#
#49
1#
#50
0#
#51
1#
#52
0#
#53
1#
#54
1"
1-
0)
0#
1*
0$
